[
    {
        "title": "Top 10 Must-Read Classics",
        "author": {
            "name": "Alice Waters",
            "uid": "user001",
            "email": "alice@example.com",
            "photo_URL": "https://example.com/photos/alice.jpg"
        },
        "summary": "A curated list of timeless classics everyone should read.",
        "photo_URL": "",
        "tag": ["Classics", "Books"],
        "readCount": ["1500", "1200", "1100"],
        "date": "2024-01-01",
        "comments": [
            {
                "author": "Bob Marley",
                "email": "bob@example.com",
                "uid": "user002",
                "comment": "Great recommendations!",
                "date": "2024-01-02"
            }
        ]
    },
    {
        "title": "The Best Fantasy Books of All Time",
        "author": {
            "name": "John Doe",
            "uid": "user003",
            "email": "john@example.com",
            "photo_URL": "https://example.com/photos/john.jpg"
        },
        "summary": "Explore the most magical fantasy worlds.",
        "photo_URL": "",
        "tag": ["Fantasy", "Books"],
        "readCount": ["2300", "2200", "2100"],
        "date": "2024-01-05",
        "comments": [
            {
                "author": "Jane Smith",
                "email": "jane@example.com",
                "uid": "user004",
                "comment": "Adding these to my reading list!",
                "date": "2024-01-06"
            }
        ]
    },
    {
        "title": "Science Fiction Novels You Can't Miss",
        "author": {
            "name": "Emily Clark",
            "uid": "user005",
            "email": "emily@example.com",
            "photo_URL": "https://example.com/photos/emily.jpg"
        },
        "summary": "The best science fiction books to blow your mind.",
        "photo_URL": "",
        "tag": ["Sci-Fi", "Books"],
        "readCount": ["3200", "3100", "3000"],
        "date": "2024-01-10",
        "comments": [
            {
                "author": "Alice Waters",
                "email": "alice@example.com",
                "uid": "user001",
                "comment": "These books are out of this world!",
                "date": "2024-01-11"
            }
        ]
    },
    {
        "title": "Historical Fiction Novels to Transport You in Time",
        "author": {
            "name": "Michael Brown",
            "uid": "user006",
            "email": "michael@example.com",
            "photo_URL": "https://example.com/photos/michael.jpg"
        },
        "summary": "Immerse yourself in the past with these historical fiction novels.",
        "photo_URL": "",
        "tag": ["Historical Fiction", "Books"],
        "readCount": ["1400", "1300", "1200"],
        "date": "2024-01-15",
        "comments": [
            {
                "author": "John Doe",
                "email": "john@example.com",
                "uid": "user003",
                "comment": "Can't wait to read these.",
                "date": "2024-01-16"
            }
        ]
    },
    {
        "title": "Books to Help You Understand Modern Politics",
        "author": {
            "name": "Samantha Lee",
            "uid": "user007",
            "email": "samantha@example.com",
            "photo_URL": "https://example.com/photos/samantha.jpg"
        },
        "summary": "An essential reading list for anyone interested in politics.",
        "photo_URL": "",
        "tag": ["Politics", "Books"],
        "readCount": ["2100", "2000", "1900"],
        "date": "2024-01-20",
        "comments": [
            {
                "author": "Emily Clark",
                "email": "emily@example.com",
                "uid": "user005",
                "comment": "Informative and engaging.",
                "date": "2024-01-21"
            }
        ]
    },
    {
        "title": "Best Mystery Novels of the Decade",
        "author": {
            "name": "David Kim",
            "uid": "user008",
            "email": "david@example.com",
            "photo_URL": "https://example.com/photos/david.jpg"
        },
        "summary": "Get lost in these thrilling mystery novels.",
        "photo_URL": "",
        "tag": ["Mystery", "Books"],
        "readCount": ["1800", "1700", "1600"],
        "date": "2024-01-25",
        "comments": [
            {
                "author": "Michael Brown",
                "email": "michael@example.com",
                "uid": "user006",
                "comment": "Absolutely gripping.",
                "date": "2024-01-26"
            }
        ]
    },
    {
        "title": "Must-Read Biographies and Memoirs",
        "author": {
            "name": "Sarah Johnson",
            "uid": "user009",
            "email": "sarah@example.com",
            "photo_URL": "https://example.com/photos/sarah.jpg"
        },
        "summary": "Inspiring stories from remarkable lives.",
        "photo_URL": "",
        "tag": ["Biographies", "Books"],
        "readCount": ["2500", "2400", "2300"],
        "date": "2024-01-30",
        "comments": [
            {
                "author": "Samantha Lee",
                "email": "samantha@example.com",
                "uid": "user007",
                "comment": "So inspirational!",
                "date": "2024-01-31"
            }
        ]
    },
    {
        "title": "A Guide to Contemporary Literature",
        "author": {
            "name": "Jessica Green",
            "uid": "user010",
            "email": "jessica@example.com",
            "photo_URL": "https://example.com/photos/jessica.jpg"
        },
        "summary": "Explore the best books in contemporary literature.",
        "photo_URL": "",
        "tag": ["Contemporary", "Books"],
        "readCount": ["1600", "1500", "1400"],
        "date": "2024-02-01",
        "comments": [
            {
                "author": "David Kim",
                "email": "david@example.com",
                "uid": "user008",
                "comment": "Found some new favorites.",
                "date": "2024-02-02"
            }
        ]
    },
    {
        "title": "Children's Books That Adults Will Love Too",
        "author": {
            "name": "William Harris",
            "uid": "user011",
            "email": "william@example.com",
            "photo_URL": "https://example.com/photos/william.jpg"
        },
        "summary": "Timeless children's books that are perfect for adults.",
        "photo_URL": "",
        "tag": ["Children's Books", "Books"],
        "readCount": ["2700", "2600", "2500"],
        "date": "2024-02-05",
        "comments": [
            {
                "author": "Sarah Johnson",
                "email": "sarah@example.com",
                "uid": "user009",
                "comment": "Such heartwarming stories.",
                "date": "2024-02-06"
            }
        ]
    },
    {
        "title": "Exploring Graphic Novels: Not Just for Kids",
        "author": {
            "name": "Chris Martin",
            "uid": "user012",
            "email": "chris@example.com",
            "photo_URL": "https://example.com/photos/chris.jpg"
        },
        "summary": "A look at the best graphic novels for adults.",
        "photo_URL": "",
        "tag": ["Graphic Novels", "Books"],
        "readCount": ["2900", "2800", "2700"],
        "date": "2024-02-10",
        "comments": [
            {
                "author": "Jessica Green",
                "email": "jessica@example.com",
                "uid": "user010",
                "comment": "Graphic novels are so underrated.",
                "date": "2024-02-11"
            }
        ]
    },
    {
        "title": "Poetry Books That Will Touch Your Soul",
        "author": {
            "name": "Karen Thompson",
            "uid": "user013",
            "email": "karen@example.com",
            "photo_URL": "https://example.com/photos/karen.jpg"
        },
        "summary": "A selection of poetry books that resonate deeply.",
        "photo_URL": "",
        "tag": ["Poetry", "Books"],
        "readCount": ["1200", "1100", "1000"],
        "date": "2024-02-15",
        "comments": [
            {
                "author": "William Harris",
                "email": "william@example.com",
                "uid": "user011",
                "comment": "These poems are so moving.",
                "date": "2024-02-16"
            }
        ]
    },
    {
        "title": "The Ultimate Guide to Book Clubs",
        "author": {
            "name": "Daniel Wilson",
            "uid": "user014",
            "email": "daniel@example.com",
            "photo_URL": "https://example.com/photos/daniel.jpg"
        },
        "summary": "Tips and tricks for starting and maintaining a book club.",
        "photo_URL": "",
        "tag": ["Book Clubs", "Books"],
        "readCount": ["1900", "1800", "1700"],
        "date": "2024-02-20",
        "comments": [
            {
                "author": "Chris Martin",
                "email": "chris@example.com",
                "uid": "user012",
                "comment": "A wonderful guide for book lovers.",
                "date": "2024-02-21"
            }
        ]
    },
    {
        "title": "Gardening Books for Every Season",
        "author": {
            "name": "Laura White",
            "uid": "user015",
            "email": "laura@example.com",
            "photo_URL": "https://example.com/photos/laura.jpg"
        },
        "summary": "Books to help you garden year-round.",
        "photo_URL": "",
        "tag": ["Gardening", "Books"],
        "readCount": ["1300", "1200", "1100"],
        "date": "2024-02-25",
        "comments": [
            {
                "author": "Karen Thompson",
                "email": "karen@example.com",
                "uid": "user013",
                "comment": "Can't wait to try these tips.",
                "date": "2024-02-26"
            }
        ]
    },
    {
        "title": "Books About the Power of Positive Thinking",
        "author": {
            "name": "Edward Adams",
            "uid": "user016",
            "email": "edward@example.com",
            "photo_URL": "https://example.com/photos/edward.jpg"
        },
        "summary": "How positivity can improve your life, through the lens of various authors.",
        "photo_URL": "",
        "tag": ["Self-help", "Books"],
        "readCount": ["2200", "2100", "2000"],
        "date": "2024-03-01",
        "comments": [
            {
                "author": "Laura White",
                "email": "laura@example.com",
                "uid": "user015",
                "comment": "This is so motivating!",
                "date": "2024-03-02"
            }
        ]
    },
    {
        "title": "Exploring the Lives of Ancient Civilizations",
        "author": {
            "name": "Robert Garcia",
            "uid": "user017",
            "email": "robert@example.com",
            "photo_URL": "https://example.com/photos/robert.jpg"
        },
        "summary": "Books that delve into the history and culture of ancient civilizations.",
        "photo_URL": "",
        "tag": ["History", "Books"],
        "readCount": ["2400", "2300", "2200"],
        "date": "2024-03-05",
        "comments": [
            {
                "author": "Edward Adams",
                "email": "edward@example.com",
                "uid": "user016",
                "comment": "A fascinating topic.",
                "date": "2024-03-06"
            }
        ]
    },
    {
        "title": "DIY Home Improvement Books for Beginners",
        "author": {
            "name": "Rebecca Taylor",
            "uid": "user018",
            "email": "rebecca@example.com",
            "photo_URL": "https://example.com/photos/rebecca.jpg"
        },
        "summary": "Books that guide you through simple home improvement projects.",
        "photo_URL": "",
        "tag": ["DIY", "Books"],
        "readCount": ["1700", "1600", "1500"],
        "date": "2024-03-10",
        "comments": [
            {
                "author": "Robert Garcia",
                "email": "robert@example.com",
                "uid": "user017",
                "comment": "Great ideas for my next project.",
                "date": "2024-03-11"
            }
        ]
    }
]
